<DOMSymbolItem xmlns:xsi="http://www.w3.org/2001/XMLSchema-instance" xmlns="http://ns.adobe.com/xfl/2008/" name="h  lowercase" itemID="5f92070d-0000061e" symbolType="graphic" lastModified="1603405591">
  <timeline>
    <DOMTimeline name="h  lowercase" currentFrame="3">
      <layers>
        <DOMLayer name="Layer 1" color="#4FFF4F" current="true" isSelected="true">
          <frames>
            <DOMFrame index="0" duration="2" keyMode="9728">
              <elements>
                <DOMShape>
                  <fills>
                    <FillStyle index="1">
                      <SolidColor/>
                    </FillStyle>
                  </fills>
                  <edges>
                    <Edge fillStyle1="1" edges="!153 38S2[157 45 160 53!160 53[163 60 166 68!166 68[171 120 173 173!173 173[174 240 173 308!173 308[183 333 184 360!184 360[186 405 186 450!186 450[186 456 186 463!186 463[351 332 490 488!490 488[503 502 518 515!518 515[526 525 531 536
!531 536[541 555 548 575!548 575[552 586 556 598!556 598[556 601 556 605!556 605[556 609 556 613!556 613[556 616 556 620!556 620[573 711 575 808!575 808[578 920 468 945!468 945[461 944 453 942!453 942[443 940 434 937!434 937[426 934 418
 930!418 930[414 927 411 923!411 923[407 919 403 915!403 915[399 911 396 908!396 908[392 900 388 893!388 893[380 879 380 863!380 863[381 848 381 833!381 833[382 829 383 825!383 825[384 821 386 818!386 818[387 814 388 810!388 810[389 806
 391 803!391 803[391 788 391 773!391 773[391 743 391 713!391 713[391 701 391 690!391 690[389 686 388 683!388 683[386 679 384 675!384 675[382 668 381 660!381 660[381 653 381 645!381 645[379 641 378 638!378 638[377 634 376 630!376 630[373
 626 370 623!370 623[367 619 364 615!364 615[361 611 359 607!359 607[357 604 356 600!356 600[353 596 350 594!350 594[344 589 338 585!338 585[331 585 324 587!324 587[319 589 316 593!316 593[292 624 270 658!270 658[243 698 226 743!226 743
[226 746 226 750!226 750[226 754 226 758!226 758[224 761 223 765!223 765[222 769 221 773!221 773[219 776 218 780!218 780[217 784 216 788!216 788[216 791 216 795!216 795[216 799 216 803!216 803[216 806 216 810!216 810[216 814 216 818!216
 818[211 838 200 855!200 855[175 893 128 895!128 895[121 894 113 892!113 892[103 890 93 887!93 887[86 884 78 880!78 880[74 876 71 873!71 873[67 869 63 865!63 865[59 861 56 858!56 858[49 846 46 834!46 834[40 817 40 798!40 798[41 786 41
 775!41 775[34 757 33 738!33 738[31 704 31 670!31 670[31 663 31 655!31 655[24 640 22 625!22 625[19 599 20 573!20 573[21 561 21 550!21 550[8 518 9 483!9 483[11 430 11 378!11 378[11 374 11 370!11 370[-2 300 1 228!1 228[5 145 11 63!11 63
[12 59 13 55!13 55[14 51 16 48!16 48[17 44 18 40!18 40[22 36 25 32!25 32[28 29 31 25!31 25[34 21 38 18!38 18[49 11 61 8!61 8[74 4 88 1!88 1|88 0!88 0[104 4 120 10!120 10[132 15 143 23!143 23[146 26 148 30!148 30[151 34 153 38"/>
                  </edges>
                </DOMShape>
              </elements>
            </DOMFrame>
            <DOMFrame index="2" duration="2" keyMode="9728">
              <elements>
                <DOMShape>
                  <fills>
                    <FillStyle index="1">
                      <SolidColor/>
                    </FillStyle>
                  </fills>
                  <edges>
                    <Edge fillStyle0="1" edges="
!417 432[366 398 308 411!308 411[243 421 186 463!186 463[175 317 178 173!178 173[179 101 152 39!152 39[148 30 143 23!143 23|88 0!88 0[43 3 20 42!20 42[15 51 14 63!14 63[1 291 14 518!14 518[16 545 19 573!19 573[33 696 45 816!45 816[52
 881 113 892!113 892[209 897 219 803!219 803[231 686 316 593!316 593|338 585!338 585[384 628 389 690!389 690[395 776 384 863!384 863[381 887 398 906!398 906[447 966 515 925!515 925[581 886 575 808!575 808[567 700 552 599!552 599[541 529
 491 487!491 487[455 458 417 432"/>
                  </edges>
                </DOMShape>
              </elements>
            </DOMFrame>
          </frames>
        </DOMLayer>
      </layers>
    </DOMTimeline>
  </timeline>
</DOMSymbolItem>