<DOMSymbolItem xmlns:xsi="http://www.w3.org/2001/XMLSchema-instance" xmlns="http://ns.adobe.com/xfl/2008/" name="L capital" itemID="5f920474-000004cf" symbolType="graphic" lastModified="1603404932">
  <timeline>
    <DOMTimeline name="L capital" currentFrame="3">
      <layers>
        <DOMLayer name="Layer 1" color="#4FFF4F" current="true" isSelected="true">
          <frames>
            <DOMFrame index="0" duration="2" keyMode="9728">
              <elements>
                <DOMShape>
                  <fills>
                    <FillStyle index="1">
                      <SolidColor/>
                    </FillStyle>
                  </fills>
                  <edges>
                    <Edge fillStyle1="1" edges="!114 0S2[130 4 146 10!146 10[158 15 169 22!169 22[209 106 209 203!209 203[208 294 192 383!192 383[192 394 192 405!192 405[192 428 192 450!192 450[192 465 192 480!192 480[190 484 189 488!189 488[188 491 187 495!187 495[185 499 184 503
!184 503[183 506 182 510!182 510[182 574 182 638!182 638[182 716 182 795!182 795[184 803 186 810!186 810[189 822 190 833!190 833[192 847 192 863!192 863[385 861 606 879!606 879[639 881 653 913!653 913[661 931 662 950!662 950[652 1026
 574 1029!574 1029[330 1036 89 1046!89 1046[72 1046 54 1040!54 1040[50 1036 47 1033!47 1033[43 1029 39 1025!39 1025[35 1021 32 1018!32 1018[17 997 17 973!17 973[17 931 17 890!17 890[17 883 17 875!17 875[0 768 0 658!0 658[0 551 17 448
!17 448[17 429 16 410!16 410[15 376 21 343!21 343[23 331 27 320!27 320[27 267 27 215!27 215[29 143 34 73!34 73[39 52 51 36!51 36[75 1 114 0"/>
                  </edges>
                </DOMShape>
              </elements>
            </DOMFrame>
            <DOMFrame index="2" duration="2" keyMode="9728">
              <elements>
                <DOMShape>
                  <fills>
                    <FillStyle index="1">
                      <SolidColor/>
                    </FillStyle>
                  </fills>
                  <edges>
                    <Edge fillStyle0="1" edges="
!48 75[30 196 23 320!23 320[22 348 19 377!19 377[0 571 8 768!8 768[10 828 15 890!15 890[19 943 27 996!27 996[30 1011 40 1025!40 1025[52 1042 72 1042!72 1042[201 1041 331 1037!331 1037[462 1032 593 1030!593 1030[627 1022 645 997!645 997
[678 949 645 900!645 900[631 881 606 879!606 879[448 866 291 864!291 864[241 863 192 863!192 863[164 670 187 479!187 479[192 442 196 406!196 406[205 306 208 203!208 203[211 107 169 22!169 22|146 10!146 10[62 -16 48 75"/>
                  </edges>
                </DOMShape>
              </elements>
            </DOMFrame>
          </frames>
        </DOMLayer>
      </layers>
    </DOMTimeline>
  </timeline>
</DOMSymbolItem>